config_utilities/__init__.py
config_utilities/config_manager.py
config_utilities/logging_util.py
config_utilities-0.3.4.dist-info/LICENSE
config_utilities-0.3.4.dist-info/METADATA
config_utilities-0.3.4.dist-info/WHEEL
config_utilities-0.3.4.dist-info/top_level.txt
config_utilities-0.3.4.dist-info/RECORD
